eplda/__init__.py
eplda/api.py
eplda/config.py
eplda/config.yaml
eplda/constants.py
eplda-0.2.3.dist-info/licenses/LICENSE
eplda-0.2.3.dist-info/METADATA
eplda-0.2.3.dist-info/WHEEL
eplda-0.2.3.dist-info/top_level.txt
eplda-0.2.3.dist-info/RECORD
