Metadata-Version: 2.4
Name: eplda
Version: 0.2.3
Summary: An unofficial lightweight Python client library for Premier League Data API
Home-page: https://github.com/zhouyuyang-joey/English-Premier-League-Data-API
Author: Zhou Yuyang
Author-email: joeyjoeyjoemail@163.com
Project-URL: Bug Reports, https://github.com/zhouyuyang-joey/English-Premier-League-Data-API/issues
Project-URL: Source, https://github.com/zhouyuyang-joey/English-Premier-League-Data-API
Project-URL: Documentation, https://github.com/zhouyuyang-joey/English-Premier-League-Data-API/blob/main/README.md
Keywords: premier-league football soccer api data statistics
Classifier: Development Status :: 4 - Beta
Classifier: Intended Audience :: Developers
Classifier: Topic :: Software Development :: Libraries :: Python Modules
Classifier: Topic :: Scientific/Engineering :: Information Analysis
Classifier: License :: OSI Approved :: MIT License
Classifier: Programming Language :: Python :: 3
Classifier: Operating System :: OS Independent
Requires-Python: >=3.7
License-File: LICENSE
Requires-Dist: requests
Requires-Dist: pandas
Requires-Dist: PyYAML
Provides-Extra: dev
Requires-Dist: pytest; extra == "dev"
Requires-Dist: pytest-cov; extra == "dev"
Requires-Dist: black; extra == "dev"
Requires-Dist: flake8; extra == "dev"
Provides-Extra: test
Requires-Dist: pytest; extra == "test"
Requires-Dist: pytest-mock; extra == "test"
Dynamic: author
Dynamic: author-email
Dynamic: classifier
Dynamic: description
Dynamic: description-content-type
Dynamic: home-page
Dynamic: keywords
Dynamic: license-file
Dynamic: project-url
Dynamic: provides-extra
Dynamic: requires-dist
Dynamic: requires-python
Dynamic: summary
